odoo8_addon_website_blog_mgmt-8.0.1.0.0.99.dev12-py2.7-nspkg.pth
odoo8_addon_website_blog_mgmt-8.0.1.0.0.99.dev12.dist-info/METADATA
odoo8_addon_website_blog_mgmt-8.0.1.0.0.99.dev12.dist-info/RECORD
odoo8_addon_website_blog_mgmt-8.0.1.0.0.99.dev12.dist-info/WHEEL
odoo8_addon_website_blog_mgmt-8.0.1.0.0.99.dev12.dist-info/namespace_packages.txt
odoo8_addon_website_blog_mgmt-8.0.1.0.0.99.dev12.dist-info/top_level.txt
odoo_addons/website_blog_mgmt/README.rst
odoo_addons/website_blog_mgmt/__init__.py
odoo_addons/website_blog_mgmt/__openerp__.py
odoo_addons/website_blog_mgmt/post_init.py
odoo_addons/website_blog_mgmt/controllers/__init__.py
odoo_addons/website_blog_mgmt/controllers/main.py
odoo_addons/website_blog_mgmt/data/website_blog_mgmt_data.xml
odoo_addons/website_blog_mgmt/i18n/bg.po
odoo_addons/website_blog_mgmt/i18n/de.po
odoo_addons/website_blog_mgmt/i18n/el_GR.po
odoo_addons/website_blog_mgmt/i18n/es.po
odoo_addons/website_blog_mgmt/i18n/eu.po
odoo_addons/website_blog_mgmt/i18n/fr.po
odoo_addons/website_blog_mgmt/i18n/it.po
odoo_addons/website_blog_mgmt/i18n/pt_BR.po
odoo_addons/website_blog_mgmt/i18n/ru.po
odoo_addons/website_blog_mgmt/i18n/sl.po
odoo_addons/website_blog_mgmt/i18n/website_blog_mgmt.pot
odoo_addons/website_blog_mgmt/models/__init__.py
odoo_addons/website_blog_mgmt/models/website_blog.py
odoo_addons/website_blog_mgmt/static/description/icon.png
odoo_addons/website_blog_mgmt/static/description/index.html
odoo_addons/website_blog_mgmt/tests/__init__.py
odoo_addons/website_blog_mgmt/tests/test_website_blog_flow.py
odoo_addons/website_blog_mgmt/views/website_blog_templates.xml
odoo_addons/website_blog_mgmt/views/website_blog_views.xml
